fdpm/__init__.py
fdpm/__main__.py
fdpm/box.py
fdpm/models.py
fdpm/util.py
fdpm-0.0.82.dist-info/entry_points.txt
fdpm-0.0.82.dist-info/LICENSE
fdpm-0.0.82.dist-info/WHEEL
fdpm-0.0.82.dist-info/METADATA
fdpm-0.0.82.dist-info/RECORD
