Metadata-Version: 2.1
Name: fdpm
Version: 0.0.82
Summary: Command line tool to install packages from f-droid.org
Home-page: https://gitlab.com/kshib/fdpm
License: AGPL-3.0-only
Author: Kshitij Bhuwad
Author-email: ksyko@pm.me
Requires-Python: >=3.6.0,<4.0.0
Classifier: License :: OSI Approved :: GNU Affero General Public License v3
Classifier: Programming Language :: Python :: 3
Classifier: Programming Language :: Python :: 3.10
Classifier: Programming Language :: Python :: 3.6
Classifier: Programming Language :: Python :: 3.7
Classifier: Programming Language :: Python :: 3.8
Classifier: Programming Language :: Python :: 3.9
Requires-Dist: python-Levenshtein (>=0.12.2,<0.13.0)
Requires-Dist: pythondialog (>=3.5.3,<4.0.0)
Requires-Dist: requests (>=2.27.1,<3.0.0)
Requires-Dist: thefuzz (>=0.19.0,<0.20.0)
Requires-Dist: tqdm (>=4.63.0,<5.0.0)
